src/__init__.py
src/recommendation.py
RetailRecom-1.0.0.dist-info/METADATA
RetailRecom-1.0.0.dist-info/WHEEL
RetailRecom-1.0.0.dist-info/top_level.txt
RetailRecom-1.0.0.dist-info/RECORD
